bananopie/__init__.py
bananopie/rpc.py
bananopie/util.py
bananopie/wallet.py
bananopie-0.1.4.2.dist-info/LICENSE
bananopie-0.1.4.2.dist-info/METADATA
bananopie-0.1.4.2.dist-info/WHEEL
bananopie-0.1.4.2.dist-info/top_level.txt
bananopie-0.1.4.2.dist-info/RECORD
