Metadata-Version: 2.1
Name: bananopie
Version: 0.1.4.2
Summary: A python library to simplify sending and receiving Banano. Also a RPC wrapper.
Home-page: https://github.com/jetstream0/bananopie
Author: John Doe
Author-email: prussia@prussia.dev
License: MIT
Classifier: Programming Language :: Python :: 3
Classifier: License :: OSI Approved :: MIT License
Classifier: Operating System :: OS Independent
Requires-Python: >=3.5
License-File: LICENSE
Requires-Dist: requests
Requires-Dist: ed25519_blake2b
